crudgen/__init__.py
crudgen/abstracts/__init__.py
crudgen/abstracts/abc.py
crudgen/abstracts/apps.py
crudgen/abstracts/endpoints.py
crudgen/abstracts/fields.py
crudgen/abstracts/models.py
crudgen/abstracts/serializers.py
crudgen/abstracts/services.py
crudgen/easy_rest.json5
crudgen-0.1.2.dist-info/WHEEL
crudgen-0.1.2.dist-info/METADATA
crudgen-0.1.2.dist-info/RECORD
