Metadata-Version: 2.1
Name: crudgen
Version: 0.1.2
Summary: a minimal CRUD code generator
Author: pouria
Author-email: pooriazmn@gmail.com
Requires-Python: >=3.7,<4.0
Classifier: Programming Language :: Python :: 3
Classifier: Programming Language :: Python :: 3.7
Classifier: Programming Language :: Python :: 3.8
Classifier: Programming Language :: Python :: 3.9
